{"cameraMode":{"drawMode":0,"name":"Shaded","section":"Shading Mode"},"sceneLighting":true,"audioPlay":false,"sceneViewState":{"m_AlwaysRefresh":false,"showFog":true,"showSkybox":true,"showFlares":true,"showImageEffects":true,"showParticleSystems":true,"showVisualEffectGraphs":true,"m_FxEnabled":true},"in2DMode":false,"pivot":{"x":-0.8142669200897217,"y":1.939134120941162,"z":-1.7775521278381348},"rotation":{"x":-0.08234672248363495,"y":-0.9176287651062012,"z":0.27858465909957888,"w":-0.27124300599098208},"size":4.340498924255371,"orthographic":false}